magic_py_ball/__init__.py
magic_py_ball-2.3.0.dist-info/LICENSE
magic_py_ball-2.3.0.dist-info/METADATA
magic_py_ball-2.3.0.dist-info/WHEEL
magic_py_ball-2.3.0.dist-info/top_level.txt
magic_py_ball-2.3.0.dist-info/RECORD
