Metadata-Version: 2.1
Name: magic-py-ball
Version: 2.3.0
Summary: A simple magic 8 ball
Home-page: https://github.com/bsoyka/magic-py-ball
Author: Ben Soyka
Author-email: bensoyka@icloud.com
License: UNKNOWN
Project-URL: Source, https://github.com/bsoyka/magic-py-ball
Project-URL: Changelog, https://github.com/bsoyka/magic-py-ball/releases
Platform: UNKNOWN
Classifier: License :: OSI Approved :: MIT License
Classifier: Operating System :: OS Independent
Classifier: Intended Audience :: Developers
Classifier: Natural Language :: English
Classifier: Programming Language :: Python
Classifier: Programming Language :: Python :: 2
Classifier: Programming Language :: Python :: 2.7
Classifier: Programming Language :: Python :: 3
Classifier: Programming Language :: Python :: 3.5
Classifier: Programming Language :: Python :: 3.6
Classifier: Programming Language :: Python :: 3.7
Classifier: Programming Language :: Python :: 3.8
Classifier: Programming Language :: Python :: 3.9
Requires-Python: >=2.7
